nkv/__init__.py
nkv/nkv.py
nkv-0.1.2.dist-info/METADATA
nkv-0.1.2.dist-info/WHEEL
nkv-0.1.2.dist-info/top_level.txt
nkv-0.1.2.dist-info/RECORD
