Metadata-Version: 2.4
Name: nkv
Version: 0.1.2
Summary: A simple data file key-value
Author: Decaptado
Requires-Dist: batata-lib==0.1.8
Dynamic: author
Dynamic: requires-dist
Dynamic: summary
